{
  "index_settings": {
    "docstore_compression": "lz4",
    "docstore_blocksize": 16384
  },
  "segments": [
    {
      "segment_id": "2f044aeb-de0f-444d-a615-3c6bf318770a",
      "max_doc": 7481,
      "deletes": null
    },
    {
      "segment_id": "cc8f8490-37af-4897-9e28-b5f482268a36",
      "max_doc": 7398,
      "deletes": null
    },
    {
      "segment_id": "a29385ac-58e0-4f59-873f-6e64e800fa50",
      "max_doc": 7244,
      "deletes": null
    }
  ],
  "schema": [
    {
      "name": "title",
      "type": "text",
      "options": {
        "indexing": {
          "record": "position",
          "fieldnorms": true,
          "tokenizer": "default"
        },
        "stored": true,
        "fast": false
      }
    },
    {
      "name": "path",
      "type": "text",
      "options": {
        "indexing": {
          "record": "position",
          "fieldnorms": true,
          "tokenizer": "default"
        },
        "stored": true,
        "fast": false
      }
    },
    {
      "name": "is_dir",
      "type": "bool",
      "options": {
        "indexed": false,
        "fieldnorms": false,
        "fast": false,
        "stored": true
      }
    }
  ],
  "opstamp": 22126
}
